<?xml version="1.0" encoding="UTF-8" standalone="yes"?>
<w:comments xmlns:wpc="http://schemas.microsoft.com/office/word/2010/wordprocessingCanvas" xmlns:cx="http://schemas.microsoft.com/office/drawing/2014/chartex" xmlns:cx1="http://schemas.microsoft.com/office/drawing/2015/9/8/chartex" xmlns:cx2="http://schemas.microsoft.com/office/drawing/2015/10/21/chartex" xmlns:cx3="http://schemas.microsoft.com/office/drawing/2016/5/9/chartex" xmlns:cx4="http://schemas.microsoft.com/office/drawing/2016/5/10/chartex" xmlns:cx5="http://schemas.microsoft.com/office/drawing/2016/5/11/chartex" xmlns:cx6="http://schemas.microsoft.com/office/drawing/2016/5/12/chartex" xmlns:cx7="http://schemas.microsoft.com/office/drawing/2016/5/13/chartex" xmlns:cx8="http://schemas.microsoft.com/office/drawing/2016/5/14/chartex" xmlns:mc="http://schemas.openxmlformats.org/markup-compatibility/2006" xmlns:aink="http://schemas.microsoft.com/office/drawing/2016/ink" xmlns:am3d="http://schemas.microsoft.com/office/drawing/2017/model3d" xmlns:o="urn:schemas-microsoft-com:office:office" xmlns:r="http://schemas.openxmlformats.org/officeDocument/2006/relationships" xmlns:m="http://schemas.openxmlformats.org/officeDocument/2006/math" xmlns:v="urn:schemas-microsoft-com:vml" xmlns:wp14="http://schemas.microsoft.com/office/word/2010/wordprocessingDrawing" xmlns:wp="http://schemas.openxmlformats.org/drawingml/2006/wordprocessingDrawing" xmlns:w10="urn:schemas-microsoft-com:office:word" xmlns:w="http://schemas.openxmlformats.org/wordprocessingml/2006/main" xmlns:w14="http://schemas.microsoft.com/office/word/2010/wordml" xmlns:w15="http://schemas.microsoft.com/office/word/2012/wordml" xmlns:w16cid="http://schemas.microsoft.com/office/word/2016/wordml/cid" xmlns:w16se="http://schemas.microsoft.com/office/word/2015/wordml/symex" xmlns:wpg="http://schemas.microsoft.com/office/word/2010/wordprocessingGroup" xmlns:wpi="http://schemas.microsoft.com/office/word/2010/wordprocessingInk" xmlns:wne="http://schemas.microsoft.com/office/word/2006/wordml" xmlns:wps="http://schemas.microsoft.com/office/word/2010/wordprocessingShape" mc:Ignorable="w14 w15 w16se w16cid wp14"><w:comment w:id="0" w:author="C" w:date="2022-05-17T21:07:00Z" w:initials="C"><w:p w14:paraId="1483713E" w14:textId="6F972984" w:rsidR="00B83D86" w:rsidRPr="00627B91" w:rsidRDefault="00B83D86" w:rsidP="00627B91"><w:pPr><w:ind w:firstLineChars="0" w:firstLine="0"/><w:rPr><w:bCs/><w:color w:val="FF0000"/><w:sz w:val="21"/><w:szCs w:val="18"/></w:rPr></w:pPr><w:r><w:rPr><w:rStyle w:val="af9"/></w:rPr><w:annotationRef/></w:r><w:r w:rsidRPr="00627B91"><w:rPr><w:rFonts w:hint="eastAsia"/><w:bCs/><w:color w:val="FF0000"/><w:sz w:val="21"/><w:szCs w:val="18"/></w:rPr><w:t>根据学位等级选择</w:t></w:r></w:p></w:comment><w:comment w:id="1" w:author="C" w:date="2022-05-17T20:46:00Z" w:initials="C"><w:p w14:paraId="4AEAC6E6" w14:textId="31B62756" w:rsidR="00B83D86" w:rsidRPr="00627B91" w:rsidRDefault="00B83D86" w:rsidP="006E13EC"><w:pPr><w:ind w:firstLineChars="0" w:firstLine="0"/><w:rPr><w:bCs/><w:color w:val="FF0000"/><w:sz w:val="21"/><w:szCs w:val="18"/></w:rPr></w:pPr><w:r><w:rPr><w:rStyle w:val="af9"/></w:rPr><w:annotationRef/></w:r><w:r w:rsidRPr="00627B91"><w:rPr><w:bCs/><w:color w:val="FF0000"/><w:sz w:val="21"/><w:szCs w:val="18"/></w:rPr><w:t>论文题目不能超过</w:t></w:r><w:r w:rsidRPr="00627B91"><w:rPr><w:bCs/><w:color w:val="FF0000"/><w:sz w:val="21"/><w:szCs w:val="18"/></w:rPr><w:t>35</w:t></w:r><w:r w:rsidRPr="00627B91"><w:rPr><w:bCs/><w:color w:val="FF0000"/><w:sz w:val="21"/><w:szCs w:val="18"/></w:rPr><w:t>个汉字</w:t></w:r></w:p></w:comment><w:comment w:id="4" w:author="C" w:date="2022-05-17T21:03:00Z" w:initials="C"><w:p w14:paraId="45C82BC0" w14:textId="6CA734DB" w:rsidR="00B83D86" w:rsidRDefault="00B83D86" w:rsidP="00C33422"><w:pPr><w:pStyle w:val="aff4"/><w:ind w:left="0" w:firstLineChars="0" w:firstLine="0"/><w:rPr><w:b/><w:bCs/><w:color w:val="FF0000"/><w:sz w:val="21"/><w:szCs w:val="18"/></w:rPr></w:pPr><w:r><w:rPr><w:rStyle w:val="af9"/></w:rPr><w:annotationRef/></w:r><w:r><w:rPr><w:rFonts w:hint="eastAsia"/><w:b/><w:bCs/><w:color w:val="FF0000"/><w:sz w:val="21"/><w:szCs w:val="18"/></w:rPr><w:t>合作导师或导师团队，至多可保留一类，如不需要删除此两行后，保持个人信息部分位于页面底端</w:t></w:r></w:p><w:p w14:paraId="2B43457C" w14:textId="77777777" w:rsidR="00B83D86" w:rsidRDefault="00B83D86" w:rsidP="00C33422"><w:pPr><w:pStyle w:val="aff4"/><w:ind w:left="0" w:firstLineChars="0" w:firstLine="0"/><w:rPr><w:b/><w:bCs/><w:color w:val="FF0000"/><w:sz w:val="21"/><w:szCs w:val="18"/></w:rPr></w:pPr></w:p><w:p w14:paraId="4ECD6CA1" w14:textId="77777777" w:rsidR="00B83D86" w:rsidRDefault="00B83D86" w:rsidP="008A6C11"><w:pPr><w:pStyle w:val="aff4"/><w:ind w:left="0" w:firstLineChars="0" w:firstLine="0"/><w:rPr><w:b/><w:bCs/><w:color w:val="FF0000"/><w:sz w:val="21"/><w:szCs w:val="18"/></w:rPr></w:pPr><w:r w:rsidRPr="00C33422"><w:rPr><w:rFonts w:hint="eastAsia"/><w:b/><w:bCs/><w:color w:val="FF0000"/><w:sz w:val="21"/><w:szCs w:val="18"/></w:rPr><w:t>以下情况可认定为申请学生的合作导师。</w:t></w:r></w:p><w:p w14:paraId="39CD3A60" w14:textId="77777777" w:rsidR="00B83D86" w:rsidRPr="00C33422" w:rsidRDefault="00B83D86" w:rsidP="00C33422"><w:pPr><w:pStyle w:val="aff4"/><w:ind w:left="0" w:firstLineChars="0" w:firstLine="0"/><w:rPr><w:b/><w:bCs/><w:color w:val="FF0000"/><w:sz w:val="21"/><w:szCs w:val="18"/></w:rPr></w:pPr><w:r w:rsidRPr="00C33422"><w:rPr><w:rFonts w:hint="eastAsia"/><w:color w:val="FF0000"/><w:sz w:val="21"/><w:szCs w:val="18"/></w:rPr><w:t>与招生简章中一致的合作导师；</w:t></w:r></w:p><w:p w14:paraId="11453F35" w14:textId="77777777" w:rsidR="00B83D86" w:rsidRPr="00D104A9" w:rsidRDefault="00B83D86" w:rsidP="00C33422"><w:pPr><w:ind w:firstLineChars="0" w:firstLine="0"/><w:rPr><w:color w:val="FF0000"/><w:sz w:val="21"/><w:szCs w:val="18"/></w:rPr></w:pPr><w:r w:rsidRPr="00D104A9"><w:rPr><w:rFonts w:hint="eastAsia"/><w:color w:val="FF0000"/><w:sz w:val="21"/><w:szCs w:val="18"/></w:rPr><w:t>CSC</w:t></w:r><w:r w:rsidRPr="00D104A9"><w:rPr><w:rFonts w:hint="eastAsia"/><w:color w:val="FF0000"/><w:sz w:val="21"/><w:szCs w:val="18"/></w:rPr><w:t>项目的合作导师；</w:t></w:r></w:p><w:p w14:paraId="28968EED" w14:textId="77777777" w:rsidR="00B83D86" w:rsidRDefault="00B83D86" w:rsidP="00C33422"><w:pPr><w:ind w:firstLineChars="0" w:firstLine="0"/><w:rPr><w:color w:val="FF0000"/><w:sz w:val="21"/><w:szCs w:val="18"/></w:rPr></w:pPr><w:r w:rsidRPr="00D104A9"><w:rPr><w:rFonts w:hint="eastAsia"/><w:color w:val="FF0000"/><w:sz w:val="21"/><w:szCs w:val="18"/></w:rPr><w:t>交叉培养项目认定的合作导师。</w:t></w:r></w:p><w:p w14:paraId="32F5D631" w14:textId="77777777" w:rsidR="00B83D86" w:rsidRDefault="00B83D86" w:rsidP="00C33422"><w:pPr><w:ind w:firstLineChars="0" w:firstLine="0"/><w:rPr><w:color w:val="FF0000"/></w:rPr></w:pPr></w:p><w:p w14:paraId="1C26E334" w14:textId="77777777" w:rsidR="00B83D86" w:rsidRDefault="00B83D86" w:rsidP="008A6C11"><w:pPr><w:pStyle w:val="a6"/><w:ind w:firstLineChars="0" w:firstLine="0"/></w:pPr><w:r w:rsidRPr="00C33422"><w:rPr><w:rFonts w:hint="eastAsia"/><w:b/><w:color w:val="FF0000"/><w:sz w:val="21"/></w:rPr><w:t>“导师团队”的书写需与招生简章保持一致</w:t></w:r></w:p></w:comment><w:comment w:id="7" w:author="C" w:date="2022-05-17T20:54:00Z" w:initials="C"><w:p w14:paraId="3AF98D73" w14:textId="510578DF" w:rsidR="00B83D86" w:rsidRPr="008A6C11" w:rsidRDefault="00B83D86" w:rsidP="008A6C11"><w:pPr><w:pStyle w:val="aff4"/><w:ind w:left="0" w:firstLineChars="0" w:firstLine="0"/><w:rPr><w:b/><w:bCs/><w:color w:val="FF0000"/><w:sz w:val="21"/><w:szCs w:val="18"/></w:rPr></w:pPr><w:r><w:rPr><w:rStyle w:val="af9"/></w:rPr><w:annotationRef/></w:r><w:r w:rsidRPr="008A6C11"><w:rPr><w:rFonts w:hint="eastAsia"/><w:b/><w:bCs/><w:color w:val="FF0000"/><w:sz w:val="21"/><w:szCs w:val="18"/></w:rPr><w:t>学术型学位：</w:t></w:r></w:p><w:p w14:paraId="6DBAF68F" w14:textId="2C633406" w:rsidR="00B83D86" w:rsidRPr="008A6C11" w:rsidRDefault="00B83D86" w:rsidP="008A6C11"><w:pPr><w:pStyle w:val="aff4"/><w:ind w:left="0" w:firstLineChars="0" w:firstLine="0"/><w:rPr><w:bCs/><w:color w:val="FF0000"/><w:sz w:val="21"/><w:szCs w:val="18"/></w:rPr></w:pPr><w:r w:rsidRPr="008A6C11"><w:rPr><w:rFonts w:hint="eastAsia"/><w:bCs/><w:color w:val="FF0000"/><w:sz w:val="21"/><w:szCs w:val="18"/></w:rPr><w:t>学科名称：</w:t></w:r><w:r w:rsidRPr="008A6C11"><w:rPr><w:rFonts w:hint="eastAsia"/><w:bCs/><w:color w:val="FF0000"/><w:sz w:val="21"/><w:szCs w:val="18"/></w:rPr><w:t>X</w:t></w:r><w:r w:rsidRPr="008A6C11"><w:rPr><w:bCs/><w:color w:val="FF0000"/><w:sz w:val="21"/><w:szCs w:val="18"/></w:rPr><w:t>XXX</w:t></w:r></w:p><w:p w14:paraId="74CF9B40" w14:textId="6461E33D" w:rsidR="00B83D86" w:rsidRPr="008A6C11" w:rsidRDefault="00B83D86" w:rsidP="008A6C11"><w:pPr><w:pStyle w:val="aff4"/><w:ind w:left="0" w:firstLineChars="0" w:firstLine="0"/><w:rPr><w:b/><w:bCs/><w:color w:val="FF0000"/><w:sz w:val="21"/><w:szCs w:val="18"/></w:rPr></w:pPr><w:r w:rsidRPr="008A6C11"><w:rPr><w:rFonts w:hint="eastAsia"/><w:b/><w:bCs/><w:color w:val="FF0000"/><w:sz w:val="21"/><w:szCs w:val="18"/></w:rPr><w:t>专业型学位：</w:t></w:r></w:p><w:p w14:paraId="46CD8647" w14:textId="05F4B5CB" w:rsidR="00B83D86" w:rsidRPr="008A6C11" w:rsidRDefault="00B83D86" w:rsidP="008A6C11"><w:pPr><w:pStyle w:val="aff4"/><w:ind w:left="0" w:firstLineChars="0" w:firstLine="0"/><w:rPr><w:bCs/><w:color w:val="FF0000"/><w:sz w:val="21"/><w:szCs w:val="18"/></w:rPr></w:pPr><w:r w:rsidRPr="008A6C11"><w:rPr><w:rFonts w:hint="eastAsia"/><w:bCs/><w:color w:val="FF0000"/><w:sz w:val="21"/><w:szCs w:val="18"/></w:rPr><w:t>类别（领域）：</w:t></w:r><w:r w:rsidRPr="008A6C11"><w:rPr><w:bCs/><w:color w:val="FF0000"/><w:sz w:val="21"/><w:szCs w:val="18"/></w:rPr><w:t>XXXX</w:t></w:r></w:p></w:comment><w:comment w:id="9" w:author="C" w:date="2022-05-18T15:26:00Z" w:initials="C"><w:p w14:paraId="567622BA" w14:textId="3A7B047F" w:rsidR="00B83D86" w:rsidRPr="00B83D86" w:rsidRDefault="00B83D86"><w:pPr><w:pStyle w:val="a6"/><w:ind w:firstLine="420"/><w:rPr><w:rFonts w:hint="eastAsia"/><w:color w:val="FF0000"/><w:sz w:val="21"/><w:szCs w:val="18"/></w:rPr></w:pPr><w:r><w:rPr><w:rStyle w:val="af9"/></w:rPr><w:annotationRef/></w:r><w:r w:rsidRPr="00B83D86"><w:rPr><w:rFonts w:hint="eastAsia"/><w:color w:val="FF0000"/><w:sz w:val="21"/><w:szCs w:val="18"/></w:rPr><w:t>月份若为个位数，前边补零</w:t></w:r></w:p></w:comment><w:comment w:id="10" w:author="C" w:date="2022-05-17T20:47:00Z" w:initials="C"><w:p w14:paraId="4638A45F" w14:textId="36D3D6A4" w:rsidR="00B83D86" w:rsidRDefault="00B83D86"><w:pPr><w:pStyle w:val="a6"/><w:ind w:firstLine="420"/></w:pPr><w:r><w:rPr><w:rStyle w:val="af9"/></w:rPr><w:annotationRef/></w:r><w:r><w:rPr><w:rFonts w:hint="eastAsia"/><w:color w:val="FF0000"/><w:sz w:val="21"/></w:rPr><w:t>此处为论文题目的英文翻译，注意单词的大小写规律，如</w:t></w:r><w:r><w:rPr><w:rFonts w:hint="eastAsia"/><w:color w:val="FF0000"/><w:sz w:val="21"/></w:rPr><w:t>Structural Design and Rapid Development of Labyrinth Drip Irrigation Emitters</w:t></w:r></w:p></w:comment><w:comment w:id="11" w:author="C" w:date="2022-05-17T20:48:00Z" w:initials="C"><w:p w14:paraId="135D9A1F" w14:textId="77777777" w:rsidR="00B83D86" w:rsidRPr="006E13EC" w:rsidRDefault="00B83D86" w:rsidP="006E13EC"><w:pPr><w:spacing w:line="360" w:lineRule="auto"/><w:ind w:firstLineChars="0" w:firstLine="0"/><w:jc w:val="center"/><w:rPr><w:color w:val="FF0000"/><w:sz w:val="21"/></w:rPr></w:pPr><w:r><w:rPr><w:rStyle w:val="af9"/></w:rPr><w:annotationRef/></w:r><w:r w:rsidRPr="006E13EC"><w:rPr><w:rFonts w:hint="eastAsia"/><w:color w:val="FF0000"/><w:sz w:val="21"/></w:rPr><w:t>此处若为硕士学位论文，使用</w:t></w:r><w:r w:rsidRPr="006E13EC"><w:rPr><w:rFonts w:hint="eastAsia"/><w:color w:val="FF0000"/><w:sz w:val="21"/></w:rPr><w:t xml:space="preserve"> </w:t></w:r><w:r w:rsidRPr="006E13EC"><w:rPr><w:color w:val="FF0000"/><w:sz w:val="21"/></w:rPr><w:t>thesis</w:t></w:r></w:p><w:p w14:paraId="23F98134" w14:textId="616D7A97" w:rsidR="00B83D86" w:rsidRPr="006E13EC" w:rsidRDefault="00B83D86" w:rsidP="006E13EC"><w:pPr><w:spacing w:line="360" w:lineRule="auto"/><w:ind w:firstLineChars="0" w:firstLine="0"/><w:jc w:val="center"/><w:rPr><w:color w:val="FF0000"/><w:sz w:val="21"/></w:rPr></w:pPr><w:r w:rsidRPr="006E13EC"><w:rPr><w:rFonts w:hint="eastAsia"/><w:color w:val="FF0000"/><w:sz w:val="21"/></w:rPr><w:t>若为博士学位论文，使用</w:t></w:r><w:r w:rsidRPr="006E13EC"><w:rPr><w:rFonts w:hint="eastAsia"/><w:color w:val="FF0000"/><w:sz w:val="21"/></w:rPr><w:t xml:space="preserve"> </w:t></w:r><w:r w:rsidRPr="006E13EC"><w:rPr><w:color w:val="FF0000"/><w:sz w:val="21"/></w:rPr><w:t>dissertation</w:t></w:r></w:p></w:comment><w:comment w:id="12" w:author="C" w:date="2022-05-17T20:57:00Z" w:initials="C"><w:p w14:paraId="69A8BC86" w14:textId="6ADE9BCD" w:rsidR="00B83D86" w:rsidRPr="00C33422" w:rsidRDefault="00B83D86" w:rsidP="008A6C11"><w:pPr><w:pStyle w:val="aff4"/><w:spacing w:line="360" w:lineRule="auto"/><w:ind w:left="0" w:firstLineChars="0" w:firstLine="0"/><w:rPr><w:b/><w:color w:val="FF0000"/><w:sz w:val="21"/></w:rPr></w:pPr><w:r><w:rPr><w:rStyle w:val="af9"/></w:rPr><w:annotationRef/></w:r><w:r w:rsidRPr="00C33422"><w:rPr><w:rFonts w:hint="eastAsia"/><w:b/><w:color w:val="FF0000"/><w:sz w:val="21"/></w:rPr><w:t>学硕：</w:t></w:r><w:r w:rsidRPr="00C33422"><w:rPr><w:rFonts w:hint="eastAsia"/><w:b/><w:color w:val="FF0000"/><w:sz w:val="32"/><w:szCs w:val="32"/></w:rPr><w:t>Master of</w:t></w:r><w:r w:rsidRPr="00C33422"><w:rPr><w:b/><w:color w:val="FF0000"/><w:sz w:val="32"/><w:szCs w:val="32"/></w:rPr><w:t xml:space="preserve"> XXXX</w:t></w:r></w:p><w:p w14:paraId="095540F7" w14:textId="1C40D909" w:rsidR="00B83D86" w:rsidRPr="00C33422" w:rsidRDefault="00B83D86" w:rsidP="00C33422"><w:pPr><w:spacing w:line="360" w:lineRule="auto"/><w:ind w:firstLineChars="0" w:firstLine="0"/><w:jc w:val="center"/><w:rPr><w:color w:val="FF0000"/><w:sz w:val="21"/></w:rPr></w:pPr><w:r w:rsidRPr="00C33422"><w:rPr><w:rFonts w:hint="eastAsia"/><w:color w:val="FF0000"/><w:sz w:val="21"/></w:rPr><w:t>其中</w:t></w:r><w:r w:rsidRPr="00C33422"><w:rPr><w:rFonts w:hint="eastAsia"/><w:color w:val="FF0000"/><w:sz w:val="21"/></w:rPr><w:t>X</w:t></w:r><w:r w:rsidRPr="00C33422"><w:rPr><w:color w:val="FF0000"/><w:sz w:val="21"/></w:rPr><w:t>XXX</w:t></w:r><w:r w:rsidRPr="00C33422"><w:rPr><w:rFonts w:hint="eastAsia"/><w:color w:val="FF0000"/><w:sz w:val="21"/></w:rPr><w:t>单词首字母大写，哲学：</w:t></w:r><w:r w:rsidRPr="00C33422"><w:rPr><w:rFonts w:hint="eastAsia"/><w:color w:val="FF0000"/><w:sz w:val="21"/></w:rPr><w:t>Philosophy</w:t></w:r><w:r w:rsidRPr="00C33422"><w:rPr><w:rFonts w:hint="eastAsia"/><w:color w:val="FF0000"/><w:sz w:val="21"/></w:rPr><w:t>；经济学：</w:t></w:r><w:r w:rsidRPr="00C33422"><w:rPr><w:rFonts w:hint="eastAsia"/><w:color w:val="FF0000"/><w:sz w:val="21"/></w:rPr><w:t>Economics</w:t></w:r><w:r w:rsidRPr="00C33422"><w:rPr><w:rFonts w:hint="eastAsia"/><w:color w:val="FF0000"/><w:sz w:val="21"/></w:rPr><w:t>；法学：</w:t></w:r><w:r w:rsidRPr="00C33422"><w:rPr><w:rFonts w:hint="eastAsia"/><w:color w:val="FF0000"/><w:sz w:val="21"/></w:rPr><w:t>Laws</w:t></w:r><w:r w:rsidRPr="00C33422"><w:rPr><w:rFonts w:hint="eastAsia"/><w:color w:val="FF0000"/><w:sz w:val="21"/></w:rPr><w:t>；教育学：</w:t></w:r><w:r w:rsidRPr="00C33422"><w:rPr><w:rFonts w:hint="eastAsia"/><w:color w:val="FF0000"/><w:sz w:val="21"/></w:rPr><w:t>Education</w:t></w:r><w:r w:rsidRPr="00C33422"><w:rPr><w:rFonts w:hint="eastAsia"/><w:color w:val="FF0000"/><w:sz w:val="21"/></w:rPr><w:t>；文学：</w:t></w:r><w:r w:rsidRPr="00C33422"><w:rPr><w:rFonts w:hint="eastAsia"/><w:color w:val="FF0000"/><w:sz w:val="21"/></w:rPr><w:t>Arts</w:t></w:r><w:r w:rsidRPr="00C33422"><w:rPr><w:rFonts w:hint="eastAsia"/><w:color w:val="FF0000"/><w:sz w:val="21"/></w:rPr><w:t>；艺术学：</w:t></w:r><w:r w:rsidRPr="00C33422"><w:rPr><w:rFonts w:hint="eastAsia"/><w:color w:val="FF0000"/><w:sz w:val="21"/></w:rPr><w:t>Arts</w:t></w:r><w:r w:rsidRPr="00C33422"><w:rPr><w:rFonts w:hint="eastAsia"/><w:color w:val="FF0000"/><w:sz w:val="21"/></w:rPr><w:t>；</w:t></w:r></w:p><w:p w14:paraId="0DAA6875" w14:textId="77777777" w:rsidR="00B83D86" w:rsidRDefault="00B83D86" w:rsidP="00C33422"><w:pPr><w:pStyle w:val="a6"/><w:ind w:firstLine="420"/><w:rPr><w:color w:val="FF0000"/><w:sz w:val="21"/></w:rPr></w:pPr><w:r w:rsidRPr="00C33422"><w:rPr><w:rFonts w:hint="eastAsia"/><w:color w:val="FF0000"/><w:sz w:val="21"/></w:rPr><w:t>理学：</w:t></w:r><w:r w:rsidRPr="00C33422"><w:rPr><w:rFonts w:hint="eastAsia"/><w:color w:val="FF0000"/><w:sz w:val="21"/></w:rPr><w:t>Science</w:t></w:r><w:r w:rsidRPr="00C33422"><w:rPr><w:rFonts w:hint="eastAsia"/><w:color w:val="FF0000"/><w:sz w:val="21"/></w:rPr><w:t>；工学：</w:t></w:r><w:r w:rsidRPr="00C33422"><w:rPr><w:rFonts w:hint="eastAsia"/><w:color w:val="FF0000"/><w:sz w:val="21"/></w:rPr><w:t>Engineering</w:t></w:r><w:r w:rsidRPr="00C33422"><w:rPr><w:rFonts w:hint="eastAsia"/><w:color w:val="FF0000"/><w:sz w:val="21"/></w:rPr><w:t>；医学：</w:t></w:r><w:r w:rsidRPr="00C33422"><w:rPr><w:rFonts w:hint="eastAsia"/><w:color w:val="FF0000"/><w:sz w:val="21"/></w:rPr><w:t>Science</w:t></w:r><w:r w:rsidRPr="00C33422"><w:rPr><w:rFonts w:hint="eastAsia"/><w:color w:val="FF0000"/><w:sz w:val="21"/></w:rPr><w:t>；管理学：</w:t></w:r><w:r w:rsidRPr="00C33422"><w:rPr><w:rFonts w:hint="eastAsia"/><w:color w:val="FF0000"/><w:sz w:val="21"/></w:rPr><w:t>Management</w:t></w:r></w:p><w:p w14:paraId="3D2A259C" w14:textId="77777777" w:rsidR="00B83D86" w:rsidRDefault="00B83D86" w:rsidP="008A6C11"><w:pPr><w:pStyle w:val="a6"/><w:ind w:firstLineChars="0" w:firstLine="0"/><w:rPr><w:color w:val="FF0000"/><w:sz w:val="21"/></w:rPr></w:pPr></w:p><w:p w14:paraId="23BB76B2" w14:textId="6E8D48AE" w:rsidR="00B83D86" w:rsidRPr="008A6C11" w:rsidRDefault="00B83D86" w:rsidP="008A6C11"><w:pPr><w:pStyle w:val="a6"/><w:ind w:firstLineChars="0" w:firstLine="0"/><w:rPr><w:color w:val="FF0000"/><w:sz w:val="21"/></w:rPr></w:pPr><w:r w:rsidRPr="008A6C11"><w:rPr><w:rFonts w:hint="eastAsia"/><w:b/><w:color w:val="FF0000"/></w:rPr><w:t>专硕：</w:t></w:r><w:r w:rsidRPr="008A6C11"><w:rPr><w:rFonts w:hint="eastAsia"/><w:b/><w:color w:val="FF0000"/><w:sz w:val="21"/></w:rPr><w:t>专业学位的英文翻译</w:t></w:r></w:p><w:p w14:paraId="4E9CF203" w14:textId="6952F52A" w:rsidR="00B83D86" w:rsidRPr="00C33422" w:rsidRDefault="00B83D86" w:rsidP="00C33422"><w:pPr><w:pStyle w:val="a6"/><w:ind w:firstLine="420"/><w:rPr><w:color w:val="FF0000"/><w:sz w:val="21"/></w:rPr></w:pPr><w:r w:rsidRPr="00C33422"><w:rPr><w:rFonts w:hint="eastAsia"/><w:color w:val="FF0000"/><w:sz w:val="21"/></w:rPr><w:t>单词首字母大写，如：工程硕士：</w:t></w:r><w:r w:rsidRPr="00C33422"><w:rPr><w:color w:val="FF0000"/><w:sz w:val="21"/></w:rPr><w:t>Master of Engineering</w:t></w:r><w:r w:rsidRPr="00C33422"><w:rPr><w:rFonts w:hint="eastAsia"/><w:color w:val="FF0000"/><w:sz w:val="21"/></w:rPr><w:t>；详见《专业学位（领域）英文标准翻译》</w:t></w:r></w:p><w:p w14:paraId="1010FDD7" w14:textId="77777777" w:rsidR="00B83D86" w:rsidRDefault="00B83D86" w:rsidP="008A6C11"><w:pPr><w:pStyle w:val="a6"/><w:ind w:firstLineChars="0" w:firstLine="0"/><w:rPr><w:b/><w:color w:val="FF0000"/></w:rPr></w:pPr></w:p><w:p w14:paraId="10C35C85" w14:textId="1439FFA4" w:rsidR="00B83D86" w:rsidRPr="00C33422" w:rsidRDefault="00B83D86" w:rsidP="008A6C11"><w:pPr><w:pStyle w:val="a6"/><w:ind w:firstLineChars="0" w:firstLine="0"/><w:rPr><w:b/><w:color w:val="FF0000"/><w:sz w:val="32"/><w:szCs w:val="32"/></w:rPr></w:pPr><w:r w:rsidRPr="00C33422"><w:rPr><w:rFonts w:hint="eastAsia"/><w:b/><w:color w:val="FF0000"/></w:rPr><w:t>学</w:t></w:r><w:r><w:rPr><w:rFonts w:hint="eastAsia"/><w:b/><w:color w:val="FF0000"/></w:rPr><w:t>术型</w:t></w:r><w:r w:rsidRPr="00C33422"><w:rPr><w:rFonts w:hint="eastAsia"/><w:b/><w:color w:val="FF0000"/></w:rPr><w:t>博</w:t></w:r><w:r><w:rPr><w:rFonts w:hint="eastAsia"/><w:b/><w:color w:val="FF0000"/></w:rPr><w:t>士</w:t></w:r><w:r w:rsidRPr="00C33422"><w:rPr><w:rFonts w:hint="eastAsia"/><w:b/><w:color w:val="FF0000"/></w:rPr><w:t>：统一为</w:t></w:r><w:r w:rsidRPr="00C33422"><w:rPr><w:b/><w:color w:val="FF0000"/><w:sz w:val="32"/><w:szCs w:val="32"/></w:rPr><w:t>Doctor of Philosophy</w:t></w:r></w:p><w:p w14:paraId="46ABE5D0" w14:textId="77777777" w:rsidR="00B83D86" w:rsidRDefault="00B83D86" w:rsidP="008A6C11"><w:pPr><w:pStyle w:val="a6"/><w:ind w:firstLineChars="0" w:firstLine="0"/><w:rPr><w:b/><w:color w:val="FF0000"/></w:rPr></w:pPr></w:p><w:p w14:paraId="783DE300" w14:textId="276E1F1A" w:rsidR="00B83D86" w:rsidRPr="00C33422" w:rsidRDefault="00B83D86" w:rsidP="008A6C11"><w:pPr><w:pStyle w:val="a6"/><w:ind w:firstLineChars="0" w:firstLine="0"/><w:rPr><w:color w:val="FF0000"/><w:sz w:val="32"/><w:szCs w:val="32"/></w:rPr></w:pPr><w:r w:rsidRPr="00C33422"><w:rPr><w:rFonts w:hint="eastAsia"/><w:b/><w:color w:val="FF0000"/></w:rPr><w:t>专业型博士：</w:t></w:r><w:r w:rsidRPr="00C33422"><w:rPr><w:b/><w:color w:val="FF0000"/><w:sz w:val="32"/><w:szCs w:val="32"/></w:rPr><w:t>Doctor of XXXXXXX</w:t></w:r></w:p><w:p w14:paraId="2BC7A4D2" w14:textId="000F5770" w:rsidR="00B83D86" w:rsidRPr="00C33422" w:rsidRDefault="00B83D86" w:rsidP="00C33422"><w:pPr><w:pStyle w:val="a6"/><w:ind w:firstLine="420"/><w:rPr><w:color w:val="FF0000"/></w:rPr></w:pPr><w:r w:rsidRPr="00C33422"><w:rPr><w:rFonts w:hint="eastAsia"/><w:color w:val="FF0000"/><w:sz w:val="21"/></w:rPr><w:t>临床医学博士：</w:t></w:r><w:r w:rsidRPr="00C33422"><w:rPr><w:color w:val="FF0000"/><w:sz w:val="21"/></w:rPr><w:t xml:space="preserve">Medicine; </w:t></w:r><w:r w:rsidRPr="00C33422"><w:rPr><w:rFonts w:hint="eastAsia"/><w:color w:val="FF0000"/><w:sz w:val="21"/></w:rPr><w:t>工程博士：</w:t></w:r><w:r w:rsidRPr="00C33422"><w:rPr><w:color w:val="FF0000"/><w:sz w:val="21"/></w:rPr><w:t>Engineering</w:t></w:r></w:p></w:comment><w:comment w:id="13" w:author="C" w:date="2022-05-17T20:49:00Z" w:initials="C"><w:p w14:paraId="771CDE8A" w14:textId="2619B68E" w:rsidR="00B83D86" w:rsidRDefault="00B83D86"><w:pPr><w:pStyle w:val="a6"/><w:ind w:firstLine="420"/></w:pPr><w:r><w:rPr><w:rStyle w:val="af9"/></w:rPr><w:annotationRef/></w:r><w:r><w:rPr><w:rFonts w:hint="eastAsia"/><w:color w:val="FF0000"/><w:sz w:val="21"/></w:rPr><w:t>此处为作者姓名全拼，名在前，姓在后，如</w:t></w:r><w:r><w:rPr><w:rFonts w:hint="eastAsia"/><w:color w:val="FF0000"/><w:sz w:val="21"/></w:rPr><w:t>Zhengying Wei</w:t></w:r></w:p></w:comment><w:comment w:id="14" w:author="C" w:date="2022-05-17T20:49:00Z" w:initials="C"><w:p w14:paraId="463F2251" w14:textId="5E144DBB" w:rsidR="00B83D86" w:rsidRDefault="00B83D86"><w:pPr><w:pStyle w:val="a6"/><w:ind w:firstLine="420"/></w:pPr><w:r><w:rPr><w:rStyle w:val="af9"/></w:rPr><w:annotationRef/></w:r><w:r><w:rPr><w:rFonts w:hint="eastAsia"/><w:color w:val="FF0000"/><w:sz w:val="21"/></w:rPr><w:t>此处为导师姓名全拼，名在前，姓在后，如</w:t></w:r><w:r><w:rPr><w:rFonts w:hint="eastAsia"/><w:color w:val="FF0000"/><w:sz w:val="21"/></w:rPr><w:t>Bingheng Lu</w:t></w:r></w:p></w:comment><w:comment w:id="15" w:author="C" w:date="2022-05-17T20:50:00Z" w:initials="C"><w:p w14:paraId="7A071C16" w14:textId="77777777" w:rsidR="00B83D86" w:rsidRDefault="00B83D86"><w:pPr><w:pStyle w:val="a6"/><w:ind w:firstLine="420"/><w:rPr><w:color w:val="FF0000"/><w:sz w:val="21"/></w:rPr></w:pPr><w:r><w:rPr><w:rStyle w:val="af9"/></w:rPr><w:annotationRef/></w:r><w:r><w:rPr><w:rFonts w:hint="eastAsia"/><w:color w:val="FF0000"/><w:sz w:val="21"/></w:rPr><w:t>合作导师及导师团队的写法须与中文题名页保持一致。若为导师姓名全拼，名在前，姓在后</w:t></w:r></w:p><w:p w14:paraId="26FEE549" w14:textId="77777777" w:rsidR="00B83D86" w:rsidRDefault="00B83D86" w:rsidP="00B83D86"><w:pPr><w:pStyle w:val="aff4"/><w:ind w:left="0" w:firstLineChars="0" w:firstLine="0"/><w:rPr><w:b/><w:bCs/><w:color w:val="FF0000"/><w:sz w:val="21"/><w:szCs w:val="18"/></w:rPr></w:pPr></w:p><w:p w14:paraId="7DCD708C" w14:textId="5AF93F51" w:rsidR="00B83D86" w:rsidRDefault="00B83D86" w:rsidP="00B83D86"><w:pPr><w:pStyle w:val="aff4"/><w:ind w:left="0" w:firstLineChars="0" w:firstLine="0"/><w:rPr><w:b/><w:bCs/><w:color w:val="FF0000"/><w:sz w:val="21"/><w:szCs w:val="18"/></w:rPr></w:pPr><w:r><w:rPr><w:rFonts w:hint="eastAsia"/><w:b/><w:bCs/><w:color w:val="FF0000"/><w:sz w:val="21"/><w:szCs w:val="18"/></w:rPr><w:t>如不需要删除此行后，保持个人信息部分位于页面底端</w:t></w:r></w:p><w:p w14:paraId="6E8F2AFB" w14:textId="61183DC8" w:rsidR="00B83D86" w:rsidRDefault="00B83D86"><w:pPr><w:pStyle w:val="a6"/><w:ind w:firstLine="480"/></w:pPr></w:p></w:comment><w:comment w:id="16" w:author="C" w:date="2022-05-17T20:51:00Z" w:initials="C"><w:p w14:paraId="5BFD4830" w14:textId="77777777" w:rsidR="00B83D86" w:rsidRPr="008A6C11" w:rsidRDefault="00B83D86"><w:pPr><w:pStyle w:val="a6"/><w:ind w:firstLine="420"/><w:rPr><w:b/><w:color w:val="FF0000"/><w:sz w:val="21"/></w:rPr></w:pPr><w:r><w:rPr><w:rStyle w:val="af9"/></w:rPr><w:annotationRef/></w:r><w:r w:rsidRPr="008A6C11"><w:rPr><w:rFonts w:hint="eastAsia"/><w:b/><w:color w:val="FF0000"/><w:sz w:val="21"/></w:rPr><w:t>学术类硕博：</w:t></w:r></w:p><w:p w14:paraId="40AB3600" w14:textId="5DA9F3DD" w:rsidR="00B83D86" w:rsidRDefault="00B83D86"><w:pPr><w:pStyle w:val="a6"/><w:ind w:firstLine="420"/><w:rPr><w:color w:val="FF0000"/><w:sz w:val="21"/></w:rPr></w:pPr><w:r><w:rPr><w:rFonts w:hint="eastAsia"/><w:color w:val="FF0000"/><w:sz w:val="21"/></w:rPr><w:t>此处为学科名称，如</w:t></w:r><w:r><w:rPr><w:rFonts w:hint="eastAsia"/><w:color w:val="FF0000"/><w:sz w:val="21"/></w:rPr><w:t>Mechanical Engineering</w:t></w:r></w:p><w:p w14:paraId="509CDE6E" w14:textId="77777777" w:rsidR="00B83D86" w:rsidRPr="008A6C11" w:rsidRDefault="00B83D86"><w:pPr><w:pStyle w:val="a6"/><w:ind w:firstLine="422"/><w:rPr><w:b/><w:color w:val="FF0000"/><w:sz w:val="21"/></w:rPr></w:pPr><w:r w:rsidRPr="008A6C11"><w:rPr><w:rFonts w:hint="eastAsia"/><w:b/><w:color w:val="FF0000"/><w:sz w:val="21"/></w:rPr><w:t>专业类硕博：</w:t></w:r></w:p><w:p w14:paraId="004B11E2" w14:textId="176F3F60" w:rsidR="00B83D86" w:rsidRDefault="00B83D86" w:rsidP="00C33422"><w:pPr><w:pStyle w:val="a6"/><w:ind w:firstLine="420"/></w:pPr><w:r><w:rPr><w:rFonts w:hint="eastAsia"/><w:color w:val="FF0000"/><w:sz w:val="21"/></w:rPr><w:t>此处填写类别（领域），如</w:t></w:r><w:r><w:rPr><w:color w:val="FF0000"/><w:sz w:val="21"/></w:rPr><w:t>Master of Engineering</w:t></w:r><w:r><w:rPr><w:rFonts w:hint="eastAsia"/><w:color w:val="FF0000"/><w:sz w:val="21"/></w:rPr><w:t>（</w:t></w:r><w:r><w:rPr><w:color w:val="FF0000"/><w:sz w:val="21"/></w:rPr><w:t>Mechanical Engineering</w:t></w:r><w:r><w:rPr><w:rFonts w:hint="eastAsia"/><w:color w:val="FF0000"/><w:sz w:val="21"/></w:rPr><w:t>），详见《专业学位（领域）英文标准翻译》</w:t></w:r></w:p></w:comment><w:comment w:id="17" w:author="C" w:date="2022-05-17T20:50:00Z" w:initials="C"><w:p w14:paraId="262DAF49" w14:textId="69119066" w:rsidR="00B83D86" w:rsidRDefault="00B83D86"><w:pPr><w:pStyle w:val="a6"/><w:ind w:firstLine="420"/></w:pPr><w:r><w:rPr><w:rStyle w:val="af9"/></w:rPr><w:annotationRef/></w:r><w:r><w:rPr><w:rFonts w:hint="eastAsia"/><w:color w:val="FF0000"/><w:sz w:val="21"/></w:rPr><w:t>此处为英文日期，月在前，年在后，如</w:t></w:r><w:r><w:rPr><w:rFonts w:hint="eastAsia"/><w:color w:val="FF0000"/><w:sz w:val="21"/></w:rPr><w:t>January 2021</w:t></w:r></w:p></w:comment><w:comment w:id="18" w:author="C" w:date="2022-05-17T21:07:00Z" w:initials="C"><w:p w14:paraId="350DE9B0" w14:textId="253BCA5D" w:rsidR="00B83D86" w:rsidRPr="00627B91" w:rsidRDefault="00B83D86" w:rsidP="00627B91"><w:pPr><w:ind w:firstLineChars="0" w:firstLine="0"/><w:rPr><w:bCs/><w:color w:val="FF0000"/><w:sz w:val="21"/><w:szCs w:val="18"/></w:rPr></w:pPr><w:r><w:rPr><w:rStyle w:val="af9"/></w:rPr><w:annotationRef/></w:r><w:r w:rsidRPr="00627B91"><w:rPr><w:rFonts w:hint="eastAsia"/><w:bCs/><w:color w:val="FF0000"/><w:sz w:val="21"/><w:szCs w:val="18"/></w:rPr><w:t>根据学位等级选择</w:t></w:r></w:p></w:comment><w:comment w:id="19" w:author="C" w:date="2022-05-17T20:51:00Z" w:initials="C"><w:p w14:paraId="41681637" w14:textId="098B0A09" w:rsidR="00B83D86" w:rsidRPr="006E13EC" w:rsidRDefault="00B83D86"><w:pPr><w:pStyle w:val="a6"/><w:ind w:firstLine="420"/><w:rPr><w:color w:val="FF0000"/><w:sz w:val="21"/></w:rPr></w:pPr><w:r><w:rPr><w:rStyle w:val="af9"/></w:rPr><w:annotationRef/></w:r><w:r w:rsidRPr="006E13EC"><w:rPr><w:color w:val="FF0000"/><w:sz w:val="21"/></w:rPr><w:t>论文题目不能超过</w:t></w:r><w:r w:rsidRPr="006E13EC"><w:rPr><w:color w:val="FF0000"/><w:sz w:val="21"/></w:rPr><w:t>35</w:t></w:r><w:r w:rsidRPr="006E13EC"><w:rPr><w:color w:val="FF0000"/><w:sz w:val="21"/></w:rPr><w:t>个汉字</w:t></w:r></w:p></w:comment><w:comment w:id="20" w:author="C" w:date="2022-05-18T16:16:00Z" w:initials="C"><w:p w14:paraId="55F2CE1D" w14:textId="77777777" w:rsidR="00E87804" w:rsidRDefault="00E87804"><w:pPr><w:pStyle w:val="a6"/><w:ind w:firstLine="420"/></w:pPr><w:r><w:rPr><w:rStyle w:val="af9"/></w:rPr><w:annotationRef/></w:r><w:r><w:rPr><w:rFonts w:hint="eastAsia"/></w:rPr><w:t>此处应为「单位职称」</w:t></w:r></w:p><w:p w14:paraId="752C5629" w14:textId="2103CB05" w:rsidR="00E87804" w:rsidRDefault="00E87804"><w:pPr><w:pStyle w:val="a6"/><w:ind w:firstLine="480"/><w:rPr><w:rFonts w:hint="eastAsia"/></w:rPr></w:pPr><w:r><w:rPr><w:rFonts w:hint="eastAsia"/></w:rPr><w:t>如「西安交通大学副教授」或「</w:t></w:r><w:r><w:rPr><w:rFonts w:hint="eastAsia"/></w:rPr><w:t>X</w:t></w:r><w:r><w:t>X</w:t></w:r><w:r><w:rPr><w:rFonts w:hint="eastAsia"/></w:rPr><w:t>研究院高工」</w:t></w:r></w:p></w:comment><w:comment w:id="21" w:author="C" w:date="2022-05-18T16:17:00Z" w:initials="C"><w:p w14:paraId="76DA0A0F" w14:textId="2B1FCBD1" w:rsidR="00E87804" w:rsidRDefault="00E87804" w:rsidP="00E87804"><w:pPr><w:pStyle w:val="a6"/><w:ind w:firstLineChars="95" w:firstLine="199"/><w:rPr><w:rFonts w:hint="eastAsia"/></w:rPr></w:pPr><w:r><w:rPr><w:rStyle w:val="af9"/></w:rPr><w:annotationRef/></w:r><w:r><w:rPr><w:rFonts w:hint="eastAsia"/></w:rPr><w:t>此处应为该委员姓名，为了使其对齐，此处应用了制表位，建议选中姓名后更改</w:t></w:r></w:p></w:comment><w:comment w:id="22" w:author="C" w:date="2022-05-17T20:51:00Z" w:initials="C"><w:p w14:paraId="25B264D5" w14:textId="518202EA" w:rsidR="0076664A" w:rsidRPr="006E13EC" w:rsidRDefault="0076664A"><w:pPr><w:pStyle w:val="a6"/><w:ind w:firstLine="420"/><w:rPr><w:color w:val="FF0000"/><w:sz w:val="21"/></w:rPr></w:pPr><w:r><w:rPr><w:rStyle w:val="af9"/></w:rPr><w:annotationRef/></w:r><w:r w:rsidRPr="006E13EC"><w:rPr><w:rFonts w:hint="eastAsia"/><w:color w:val="FF0000"/><w:sz w:val="21"/></w:rPr><w:t>这几个字保留，不删除</w:t></w:r></w:p></w:comment><w:comment w:id="23" w:author="C" w:date="2022-05-18T16:24:00Z" w:initials="C"><w:p w14:paraId="5DC67FEF" w14:textId="18920D5C" w:rsidR="00E87804" w:rsidRPr="00207A80" w:rsidRDefault="00E87804"><w:pPr><w:pStyle w:val="a6"/><w:ind w:firstLine="420"/><w:rPr><w:rFonts w:hint="eastAsia"/><w:b/><w:color w:val="FF0000"/></w:rPr></w:pPr><w:r><w:rPr><w:rStyle w:val="af9"/></w:rPr><w:annotationRef/></w:r><w:r w:rsidRPr="00207A80"><w:rPr><w:rFonts w:hint="eastAsia"/><w:b/><w:color w:val="FF0000"/></w:rPr><w:t>答辩完成后，提交至图书馆版本需要所有委员在自己姓名旁边签字</w:t></w:r></w:p></w:comment><w:comment w:id="24" w:author="C" w:date="2022-05-18T15:34:00Z" w:initials="C"><w:p w14:paraId="728B0184" w14:textId="7D87E141" w:rsidR="00B83D86" w:rsidRDefault="00B83D86"><w:pPr><w:pStyle w:val="a6"/><w:ind w:firstLine="420"/><w:rPr><w:rFonts w:hint="eastAsia"/></w:rPr></w:pPr><w:r><w:rPr><w:rStyle w:val="af9"/></w:rPr><w:annotationRef/></w:r><w:r><w:rPr><w:rFonts w:hint="eastAsia"/></w:rPr><w:t>若月份为个位数，补零</w:t></w:r></w:p></w:comment><w:comment w:id="25" w:author="C" w:date="2022-05-18T15:33:00Z" w:initials="C"><w:p w14:paraId="4D02DB96" w14:textId="77777777" w:rsidR="00B83D86" w:rsidRDefault="00B83D86"><w:pPr><w:pStyle w:val="a6"/><w:ind w:firstLine="420"/></w:pPr><w:r><w:rPr><w:rStyle w:val="af9"/></w:rPr><w:annotationRef/></w:r><w:r><w:rPr><w:rFonts w:hint="eastAsia"/></w:rPr><w:t>非涉密论文写清答辩地点，如「西安交通大学主楼</w:t></w:r><w:r><w:rPr><w:rFonts w:hint="eastAsia"/></w:rPr><w:t>A</w:t></w:r><w:r><w:rPr><w:rFonts w:hint="eastAsia"/></w:rPr><w:t>座</w:t></w:r><w:r><w:rPr><w:rFonts w:hint="eastAsia"/></w:rPr><w:t>1</w:t></w:r><w:r><w:t>01</w:t></w:r><w:r><w:rPr><w:rFonts w:hint="eastAsia"/></w:rPr><w:t>室」</w:t></w:r></w:p><w:p w14:paraId="736AF888" w14:textId="77777777" w:rsidR="00B83D86" w:rsidRDefault="00B83D86"><w:pPr><w:pStyle w:val="a6"/><w:ind w:firstLine="480"/></w:pPr></w:p><w:p w14:paraId="563DFC7D" w14:textId="6889E58B" w:rsidR="00B83D86" w:rsidRDefault="00B83D86"><w:pPr><w:pStyle w:val="a6"/><w:ind w:firstLine="480"/><w:rPr><w:rFonts w:hint="eastAsia"/></w:rPr></w:pPr><w:r><w:rPr><w:rFonts w:hint="eastAsia"/></w:rPr><w:t>涉密论文只写「西安交通大学」即可</w:t></w:r></w:p></w:comment><w:comment w:id="62" w:author="C" w:date="2022-05-17T21:10:00Z" w:initials="C"><w:p w14:paraId="0AFE6DDE" w14:textId="1479AB03" w:rsidR="00B83D86" w:rsidRDefault="00B83D86" w:rsidP="004D6B90"><w:pPr><w:ind w:firstLine="420"/></w:pPr><w:r><w:rPr><w:rStyle w:val="af9"/></w:rPr><w:annotationRef/></w:r><w:r><w:rPr><w:sz w:val="21"/></w:rPr><w:t>关键词由</w:t></w:r><w:r><w:rPr><w:kern w:val="0"/><w:sz w:val="21"/></w:rPr><w:t>3</w:t></w:r><w:r><w:rPr><w:kern w:val="0"/><w:sz w:val="21"/></w:rPr><w:t>～</w:t></w:r><w:r><w:rPr><w:kern w:val="0"/><w:sz w:val="21"/></w:rPr><w:t>5</w:t></w:r><w:r><w:rPr><w:sz w:val="21"/></w:rPr><w:t>个组成。关键词应从《汉语主题词表》中摘选，当《汉语主题词表》的词不足以反映主题时，可由申请人设计关键词，但须加注。</w:t></w:r><w:r><w:rPr><w:kern w:val="0"/><w:sz w:val="21"/></w:rPr><w:t>每一关键词之间用分号分开，最后一个关键词后不打标点符号。</w:t></w:r><w:r><w:rPr><w:sz w:val="21"/></w:rPr><w:t>由申请人设计的关键词，须在该关键词的右上角标注</w:t></w:r><w:r><w:rPr><w:sz w:val="21"/></w:rPr><w:t>*</w:t></w:r><w:r><w:rPr><w:sz w:val="21"/></w:rPr><w:t>，并在该页的页脚处注明</w:t></w:r><w:r><w:rPr><w:sz w:val="21"/></w:rPr><w:t>“*</w:t></w:r><w:r><w:rPr><w:sz w:val="21"/></w:rPr><w:t>表示非汉语主题词</w:t></w:r><w:r><w:rPr><w:sz w:val="21"/></w:rPr><w:t>”</w:t></w:r><w:r><w:rPr><w:sz w:val="21"/></w:rPr><w:t>。</w:t></w:r></w:p></w:comment><w:comment w:id="63" w:author="C" w:date="2022-05-17T21:10:00Z" w:initials="C"><w:p w14:paraId="565FD398" w14:textId="6020B7F1" w:rsidR="00B83D86" w:rsidRDefault="00B83D86"><w:pPr><w:pStyle w:val="a6"/><w:ind w:firstLine="420"/></w:pPr><w:r><w:rPr><w:rStyle w:val="af9"/></w:rPr><w:annotationRef/></w:r><w:r><w:rPr><w:sz w:val="21"/></w:rPr><w:t>论文类型包括：</w:t></w:r><w:r><w:rPr><w:rFonts w:hint="eastAsia"/><w:sz w:val="21"/></w:rPr><w:t>a.</w:t></w:r><w:r><w:rPr><w:rFonts w:hint="eastAsia"/><w:sz w:val="21"/></w:rPr><w:t>理论研究（</w:t></w:r><w:r><w:rPr><w:rFonts w:hint="eastAsia"/><w:sz w:val="21"/></w:rPr><w:t>Theoretical Research)</w:t></w:r><w:r><w:rPr><w:rFonts w:hint="eastAsia"/><w:sz w:val="21"/></w:rPr><w:t>；</w:t></w:r><w:r><w:rPr><w:rFonts w:hint="eastAsia"/><w:sz w:val="21"/></w:rPr><w:t>b.</w:t></w:r><w:r><w:rPr><w:rFonts w:hint="eastAsia"/><w:sz w:val="21"/></w:rPr><w:t>应用基础</w:t></w:r><w:r><w:rPr><w:rFonts w:hint="eastAsia"/><w:sz w:val="21"/></w:rPr><w:t>(Application Fundamentals)</w:t></w:r><w:r><w:rPr><w:rFonts w:hint="eastAsia"/><w:sz w:val="21"/></w:rPr><w:t>；</w:t></w:r><w:r><w:rPr><w:rFonts w:hint="eastAsia"/><w:sz w:val="21"/></w:rPr><w:t>c.</w:t></w:r><w:r><w:rPr><w:rFonts w:hint="eastAsia"/><w:sz w:val="21"/></w:rPr><w:t>应用研究</w:t></w:r><w:r><w:rPr><w:rFonts w:hint="eastAsia"/><w:sz w:val="21"/></w:rPr><w:t>(Application Research)</w:t></w:r><w:r><w:rPr><w:rFonts w:hint="eastAsia"/><w:sz w:val="21"/></w:rPr><w:t>；</w:t></w:r><w:r><w:rPr><w:rFonts w:hint="eastAsia"/><w:sz w:val="21"/></w:rPr><w:t>d.</w:t></w:r><w:r><w:rPr><w:rFonts w:hint="eastAsia"/><w:sz w:val="21"/></w:rPr><w:t>研究报告</w:t></w:r><w:r><w:rPr><w:rFonts w:hint="eastAsia"/><w:sz w:val="21"/></w:rPr><w:t>(Research Report)</w:t></w:r><w:r><w:rPr><w:rFonts w:hint="eastAsia"/><w:sz w:val="21"/></w:rPr><w:t>；</w:t></w:r><w:r><w:rPr><w:rFonts w:hint="eastAsia"/><w:sz w:val="21"/></w:rPr><w:t>e.</w:t></w:r><w:r><w:rPr><w:rFonts w:hint="eastAsia"/><w:sz w:val="21"/></w:rPr><w:t>设计报告</w:t></w:r><w:r><w:rPr><w:rFonts w:hint="eastAsia"/><w:sz w:val="21"/></w:rPr><w:t>(Design Report)</w:t></w:r><w:r><w:rPr><w:rFonts w:hint="eastAsia"/><w:sz w:val="21"/></w:rPr><w:t>；</w:t></w:r><w:r><w:rPr><w:rFonts w:hint="eastAsia"/><w:sz w:val="21"/></w:rPr><w:t>f.</w:t></w:r><w:r><w:rPr><w:rFonts w:hint="eastAsia"/><w:sz w:val="21"/></w:rPr><w:t>案例分析</w:t></w:r><w:r><w:rPr><w:rFonts w:hint="eastAsia"/><w:sz w:val="21"/></w:rPr><w:t>(Case Study)</w:t></w:r><w:r><w:rPr><w:rFonts w:hint="eastAsia"/><w:sz w:val="21"/></w:rPr><w:t>；</w:t></w:r><w:r><w:rPr><w:rFonts w:hint="eastAsia"/><w:sz w:val="21"/></w:rPr><w:t>g.</w:t></w:r><w:r><w:rPr><w:rFonts w:hint="eastAsia"/><w:sz w:val="21"/></w:rPr><w:t>调研报告</w:t></w:r><w:r><w:rPr><w:rFonts w:hint="eastAsia"/><w:sz w:val="21"/></w:rPr><w:t>(Investigation Report)</w:t></w:r><w:r><w:rPr><w:rFonts w:hint="eastAsia"/><w:sz w:val="21"/></w:rPr><w:t>；</w:t></w:r><w:r><w:rPr><w:rFonts w:hint="eastAsia"/><w:sz w:val="21"/></w:rPr><w:t>h.</w:t></w:r><w:r><w:rPr><w:rFonts w:hint="eastAsia"/><w:sz w:val="21"/></w:rPr><w:t>产品研发</w:t></w:r><w:r><w:rPr><w:rFonts w:hint="eastAsia"/><w:sz w:val="21"/></w:rPr><w:t>(Product Development)</w:t></w:r><w:r><w:rPr><w:rFonts w:hint="eastAsia"/><w:sz w:val="21"/></w:rPr><w:t>；</w:t></w:r><w:r><w:rPr><w:rFonts w:hint="eastAsia"/><w:sz w:val="21"/></w:rPr><w:t>i.</w:t></w:r><w:r><w:rPr><w:rFonts w:hint="eastAsia"/><w:sz w:val="21"/></w:rPr><w:t>工程设计</w:t></w:r><w:r><w:rPr><w:rFonts w:hint="eastAsia"/><w:sz w:val="21"/></w:rPr><w:t>(Engineering Design)</w:t></w:r><w:r><w:rPr><w:rFonts w:hint="eastAsia"/><w:sz w:val="21"/></w:rPr><w:t>；</w:t></w:r><w:r><w:rPr><w:rFonts w:hint="eastAsia"/><w:sz w:val="21"/></w:rPr><w:t>j.</w:t></w:r><w:r><w:rPr><w:rFonts w:hint="eastAsia"/><w:sz w:val="21"/></w:rPr><w:t>工程</w:t></w:r><w:r><w:rPr><w:rFonts w:hint="eastAsia"/><w:sz w:val="21"/></w:rPr><w:t>/</w:t></w:r><w:r><w:rPr><w:rFonts w:hint="eastAsia"/><w:sz w:val="21"/></w:rPr><w:t>项目管理</w:t></w:r><w:r><w:rPr><w:rFonts w:hint="eastAsia"/><w:sz w:val="21"/></w:rPr><w:t>(Engineering/Project Management)</w:t></w:r><w:r><w:rPr><w:rFonts w:hint="eastAsia"/><w:sz w:val="21"/></w:rPr><w:t>；</w:t></w:r><w:r><w:rPr><w:rFonts w:hint="eastAsia"/><w:sz w:val="21"/></w:rPr><w:t>k.</w:t></w:r><w:r><w:rPr><w:rFonts w:hint="eastAsia"/><w:sz w:val="21"/></w:rPr><w:t>其它（</w:t></w:r><w:r><w:rPr><w:rFonts w:hint="eastAsia"/><w:sz w:val="21"/></w:rPr><w:t>Others</w:t></w:r><w:r><w:rPr><w:rFonts w:hint="eastAsia"/><w:sz w:val="21"/></w:rPr><w:t>）。</w:t></w:r></w:p></w:comment><w:comment w:id="99" w:author="C" w:date="2022-05-18T16:30:00Z" w:initials="C"><w:p w14:paraId="2FB2274A" w14:textId="4A0418DA" w:rsidR="00207A80" w:rsidRPr="00207A80" w:rsidRDefault="00207A80" w:rsidP="00207A80"><w:pPr><w:ind w:firstLineChars="0" w:firstLine="0"/><w:jc w:val="right"/><w:rPr><w:b/></w:rPr></w:pPr><w:r><w:rPr><w:rStyle w:val="af9"/></w:rPr><w:annotationRef/></w:r><w:r w:rsidRPr="00207A80"><w:rPr><w:rFonts w:hint="eastAsia"/><w:b/><w:bCs/><w:color w:val="FF0000"/><w:sz w:val="21"/><w:szCs w:val="18"/></w:rPr><w:t>务必选择页眉的学位等级</w:t></w:r></w:p></w:comment><w:comment w:id="102" w:author="C" w:date="2022-05-17T21:09:00Z" w:initials="C"><w:p w14:paraId="5DD614B1" w14:textId="77777777" w:rsidR="00B83D86" w:rsidRDefault="00B83D86" w:rsidP="004D6B90"><w:pPr><w:spacing w:line="240" w:lineRule="auto"/><w:ind w:firstLineChars="0" w:firstLine="0"/></w:pPr><w:r><w:rPr><w:rStyle w:val="af9"/></w:rPr><w:annotationRef/></w:r><w:r><w:t>英文摘要撰写要求如下：</w:t></w:r><w:r><w:rPr><w:rStyle w:val="af9"/></w:rPr><w:annotationRef/></w:r></w:p><w:p w14:paraId="78E49F91" w14:textId="77777777" w:rsidR="00B83D86" w:rsidRDefault="00B83D86" w:rsidP="004D6B90"><w:pPr><w:spacing w:line="240" w:lineRule="auto"/><w:ind w:firstLineChars="0" w:firstLine="0"/></w:pPr><w:r><w:t>（</w:t></w:r><w:r><w:t>1</w:t></w:r><w:r><w:t>）用词准确</w:t></w:r><w:r><w:rPr><w:rFonts w:hint="eastAsia"/></w:rPr><w:t>，符合语法</w:t></w:r><w:r><w:t>；</w:t></w:r></w:p><w:p w14:paraId="75CA72A3" w14:textId="77777777" w:rsidR="00B83D86" w:rsidRDefault="00B83D86" w:rsidP="004D6B90"><w:pPr><w:spacing w:line="240" w:lineRule="auto"/><w:ind w:firstLineChars="0" w:firstLine="0"/></w:pPr><w:r><w:t>（</w:t></w:r><w:r><w:t>2</w:t></w:r><w:r><w:t>）关键词按相应专业的标准术语写出，尽量从《英语主题词表》中摘选</w:t></w:r><w:r><w:rPr><w:rFonts w:hint="eastAsia"/></w:rPr><w:t>；</w:t></w:r></w:p><w:p w14:paraId="729CC5E2" w14:textId="77777777" w:rsidR="00B83D86" w:rsidRDefault="00B83D86" w:rsidP="004D6B90"><w:pPr><w:spacing w:line="240" w:lineRule="auto"/><w:ind w:firstLineChars="0" w:firstLine="0"/></w:pPr><w:r><w:t>（</w:t></w:r><w:r><w:rPr><w:rFonts w:hint="eastAsia"/></w:rPr><w:t>3</w:t></w:r><w:r><w:t>）如果论文的主体工作得到了有关基金资助，应用英文在摘要第一页的页脚处标注：本研究得到某某基金（编号：）资助</w:t></w:r><w:r><w:rPr><w:rFonts w:hint="eastAsia"/></w:rPr><w:t>；</w:t></w:r></w:p><w:p w14:paraId="036053E2" w14:textId="77777777" w:rsidR="00B83D86" w:rsidRDefault="00B83D86" w:rsidP="004D6B90"><w:pPr><w:spacing w:line="240" w:lineRule="auto"/><w:ind w:firstLineChars="0" w:firstLine="0"/></w:pPr><w:r><w:t>中文摘要和英文摘要均不要求学位申请人及其指导教师签字</w:t></w:r><w:r><w:rPr><w:rFonts w:hint="eastAsia"/></w:rPr><w:t>。</w:t></w:r></w:p><w:p w14:paraId="6E141BF4" w14:textId="1F3A051B" w:rsidR="00B83D86" w:rsidRDefault="00B83D86" w:rsidP="004D6B90"><w:pPr><w:widowControl/><w:spacing w:line="240" w:lineRule="auto"/><w:ind w:firstLineChars="0" w:firstLine="0"/><w:jc w:val="left"/></w:pPr><w:r><w:t>摘要</w:t></w:r><w:r><w:rPr><w:spacing w:val="-6"/></w:rPr><w:t>正文</w:t></w:r><w:r><w:rPr><w:kern w:val="0"/></w:rPr><w:t>每段</w:t></w:r><w:r><w:rPr><w:color w:val="FF0000"/><w:kern w:val="0"/></w:rPr><w:t>开头不空格，每段之间空一行</w:t></w:r><w:r><w:rPr><w:kern w:val="0"/></w:rPr><w:t>；</w:t></w:r></w:p></w:comment><w:comment w:id="103" w:author="C" w:date="2022-05-17T21:08:00Z" w:initials="C"><w:p w14:paraId="73220A17" w14:textId="27033BF1" w:rsidR="00B83D86" w:rsidRDefault="00B83D86" w:rsidP="004D6B90"><w:pPr><w:ind w:firstLineChars="0" w:firstLine="0"/></w:pPr><w:r><w:rPr><w:rStyle w:val="af9"/></w:rPr><w:annotationRef/></w:r><w:r><w:rPr><w:kern w:val="0"/><w:sz w:val="21"/></w:rPr><w:t>每个关键词组的第一个字母大写，其余为小写，每一关键词之间用分号分开，最后一个关键词后不打标点符号。</w:t></w:r><w:r><w:rPr><w:rFonts w:hint="eastAsia"/><w:kern w:val="0"/><w:sz w:val="21"/></w:rPr><w:t>例如：</w:t></w:r><w:r><w:rPr><w:rFonts w:hint="eastAsia"/><w:sz w:val="21"/></w:rPr><w:t>Drip irrigation emitter; RP&amp;M; H</w:t></w:r><w:r><w:rPr><w:sz w:val="21"/></w:rPr><w:t>ydraulics</w:t></w:r><w:r><w:rPr><w:rFonts w:hint="eastAsia"/><w:sz w:val="21"/></w:rPr><w:t>; Labyrinth flow channel</w:t></w:r></w:p></w:comment><w:comment w:id="104" w:author="C" w:date="2022-05-17T21:08:00Z" w:initials="C"><w:p w14:paraId="5956F34E" w14:textId="77777777" w:rsidR="00B83D86" w:rsidRDefault="00B83D86" w:rsidP="004D6B90"><w:pPr><w:ind w:firstLineChars="0" w:firstLine="0"/><w:rPr><w:sz w:val="21"/></w:rPr></w:pPr><w:r><w:rPr><w:rStyle w:val="af9"/></w:rPr><w:annotationRef/></w:r><w:r><w:rPr><w:sz w:val="21"/></w:rPr><w:t>须与中文摘要中的论文类型一致</w:t></w:r><w:r><w:rPr><w:rFonts w:hint="eastAsia"/><w:sz w:val="21"/></w:rPr><w:t>；</w:t></w:r><w:r><w:rPr><w:kern w:val="0"/><w:sz w:val="21"/></w:rPr><w:t>每个单词第一个字母大写，其余为小写。</w:t></w:r><w:r><w:rPr><w:rFonts w:hint="eastAsia"/><w:kern w:val="0"/><w:sz w:val="21"/></w:rPr><w:t>例如：</w:t></w:r><w:r><w:rPr><w:rFonts w:hint="eastAsia"/><w:sz w:val="21"/></w:rPr><w:t>A</w:t></w:r><w:r><w:rPr><w:sz w:val="21"/></w:rPr><w:t>ppli</w:t></w:r><w:r><w:rPr><w:rFonts w:hint="eastAsia"/><w:sz w:val="21"/></w:rPr><w:t>ed Research</w:t></w:r></w:p><w:p w14:paraId="7BA94B37" w14:textId="77C0D0F2" w:rsidR="00B83D86" w:rsidRDefault="00B83D86"><w:pPr><w:pStyle w:val="a6"/><w:ind w:firstLine="420"/></w:pPr><w:r><w:rPr><w:sz w:val="21"/></w:rPr><w:t>论文类型包括：</w:t></w:r><w:r><w:rPr><w:rFonts w:hint="eastAsia"/><w:sz w:val="21"/></w:rPr><w:t>a.</w:t></w:r><w:r><w:rPr><w:rFonts w:hint="eastAsia"/><w:sz w:val="21"/></w:rPr><w:t>理论研究（</w:t></w:r><w:r><w:rPr><w:rFonts w:hint="eastAsia"/><w:sz w:val="21"/></w:rPr><w:t>Theoretical Research)</w:t></w:r><w:r><w:rPr><w:rFonts w:hint="eastAsia"/><w:sz w:val="21"/></w:rPr><w:t>；</w:t></w:r><w:r><w:rPr><w:rFonts w:hint="eastAsia"/><w:sz w:val="21"/></w:rPr><w:t>b.</w:t></w:r><w:r><w:rPr><w:rFonts w:hint="eastAsia"/><w:sz w:val="21"/></w:rPr><w:t>应用基础</w:t></w:r><w:r><w:rPr><w:rFonts w:hint="eastAsia"/><w:sz w:val="21"/></w:rPr><w:t>(Application Fundamentals)</w:t></w:r><w:r><w:rPr><w:rFonts w:hint="eastAsia"/><w:sz w:val="21"/></w:rPr><w:t>；</w:t></w:r><w:r><w:rPr><w:rFonts w:hint="eastAsia"/><w:sz w:val="21"/></w:rPr><w:t>c.</w:t></w:r><w:r><w:rPr><w:rFonts w:hint="eastAsia"/><w:sz w:val="21"/></w:rPr><w:t>应用研究</w:t></w:r><w:r><w:rPr><w:rFonts w:hint="eastAsia"/><w:sz w:val="21"/></w:rPr><w:t>(Application Research)</w:t></w:r><w:r><w:rPr><w:rFonts w:hint="eastAsia"/><w:sz w:val="21"/></w:rPr><w:t>；</w:t></w:r><w:r><w:rPr><w:rFonts w:hint="eastAsia"/><w:sz w:val="21"/></w:rPr><w:t>d.</w:t></w:r><w:r><w:rPr><w:rFonts w:hint="eastAsia"/><w:sz w:val="21"/></w:rPr><w:t>研究报告</w:t></w:r><w:r><w:rPr><w:rFonts w:hint="eastAsia"/><w:sz w:val="21"/></w:rPr><w:t>(Research Report)</w:t></w:r><w:r><w:rPr><w:rFonts w:hint="eastAsia"/><w:sz w:val="21"/></w:rPr><w:t>；</w:t></w:r><w:r><w:rPr><w:rFonts w:hint="eastAsia"/><w:sz w:val="21"/></w:rPr><w:t>e.</w:t></w:r><w:r><w:rPr><w:rFonts w:hint="eastAsia"/><w:sz w:val="21"/></w:rPr><w:t>设计报告</w:t></w:r><w:r><w:rPr><w:rFonts w:hint="eastAsia"/><w:sz w:val="21"/></w:rPr><w:t>(Design Report)</w:t></w:r><w:r><w:rPr><w:rFonts w:hint="eastAsia"/><w:sz w:val="21"/></w:rPr><w:t>；</w:t></w:r><w:r><w:rPr><w:rFonts w:hint="eastAsia"/><w:sz w:val="21"/></w:rPr><w:t>f.</w:t></w:r><w:r><w:rPr><w:rFonts w:hint="eastAsia"/><w:sz w:val="21"/></w:rPr><w:t>案例分析</w:t></w:r><w:r><w:rPr><w:rFonts w:hint="eastAsia"/><w:sz w:val="21"/></w:rPr><w:t>(Case Study)</w:t></w:r><w:r><w:rPr><w:rFonts w:hint="eastAsia"/><w:sz w:val="21"/></w:rPr><w:t>；</w:t></w:r><w:r><w:rPr><w:rFonts w:hint="eastAsia"/><w:sz w:val="21"/></w:rPr><w:t>g.</w:t></w:r><w:r><w:rPr><w:rFonts w:hint="eastAsia"/><w:sz w:val="21"/></w:rPr><w:t>调研报告</w:t></w:r><w:r><w:rPr><w:rFonts w:hint="eastAsia"/><w:sz w:val="21"/></w:rPr><w:t>(Investigation Report)</w:t></w:r><w:r><w:rPr><w:rFonts w:hint="eastAsia"/><w:sz w:val="21"/></w:rPr><w:t>；</w:t></w:r><w:r><w:rPr><w:rFonts w:hint="eastAsia"/><w:sz w:val="21"/></w:rPr><w:t>h.</w:t></w:r><w:r><w:rPr><w:rFonts w:hint="eastAsia"/><w:sz w:val="21"/></w:rPr><w:t>产品研发</w:t></w:r><w:r><w:rPr><w:rFonts w:hint="eastAsia"/><w:sz w:val="21"/></w:rPr><w:t>(Product Development)</w:t></w:r><w:r><w:rPr><w:rFonts w:hint="eastAsia"/><w:sz w:val="21"/></w:rPr><w:t>；</w:t></w:r><w:r><w:rPr><w:rFonts w:hint="eastAsia"/><w:sz w:val="21"/></w:rPr><w:t>i.</w:t></w:r><w:r><w:rPr><w:rFonts w:hint="eastAsia"/><w:sz w:val="21"/></w:rPr><w:t>工程设计</w:t></w:r><w:r><w:rPr><w:rFonts w:hint="eastAsia"/><w:sz w:val="21"/></w:rPr><w:t>(Engineering Design)</w:t></w:r><w:r><w:rPr><w:rFonts w:hint="eastAsia"/><w:sz w:val="21"/></w:rPr><w:t>；</w:t></w:r><w:r><w:rPr><w:rFonts w:hint="eastAsia"/><w:sz w:val="21"/></w:rPr><w:t>j.</w:t></w:r><w:r><w:rPr><w:rFonts w:hint="eastAsia"/><w:sz w:val="21"/></w:rPr><w:t>工程</w:t></w:r><w:r><w:rPr><w:rFonts w:hint="eastAsia"/><w:sz w:val="21"/></w:rPr><w:t>/</w:t></w:r><w:r><w:rPr><w:rFonts w:hint="eastAsia"/><w:sz w:val="21"/></w:rPr><w:t>项目管理</w:t></w:r><w:r><w:rPr><w:rFonts w:hint="eastAsia"/><w:sz w:val="21"/></w:rPr><w:t>(Engineering/Project Management)</w:t></w:r><w:r><w:rPr><w:rFonts w:hint="eastAsia"/><w:sz w:val="21"/></w:rPr><w:t>；</w:t></w:r><w:r><w:rPr><w:rFonts w:hint="eastAsia"/><w:sz w:val="21"/></w:rPr><w:t>k.</w:t></w:r><w:r><w:rPr><w:rFonts w:hint="eastAsia"/><w:sz w:val="21"/></w:rPr><w:t>其它（</w:t></w:r><w:r><w:rPr><w:rFonts w:hint="eastAsia"/><w:sz w:val="21"/></w:rPr><w:t>Others</w:t></w:r><w:r><w:rPr><w:rFonts w:hint="eastAsia"/><w:sz w:val="21"/></w:rPr><w:t>）。</w:t></w:r></w:p></w:comment><w:comment w:id="105" w:author="C" w:date="2022-05-17T21:11:00Z" w:initials="C"><w:p w14:paraId="42BE908B" w14:textId="6A24A3BB" w:rsidR="00B83D86" w:rsidRDefault="00B83D86"><w:pPr><w:pStyle w:val="a6"/><w:ind w:firstLine="420"/></w:pPr><w:r><w:rPr><w:rStyle w:val="af9"/></w:rPr><w:annotationRef/></w:r><w:r><w:rPr><w:rFonts w:hint="eastAsia"/></w:rPr><w:t>中文目录至多显示三级标题，正文修改后选择目录按</w:t></w:r><w:r><w:rPr><w:rFonts w:hint="eastAsia"/></w:rPr><w:t xml:space="preserve"> </w:t></w:r><w:r><w:t xml:space="preserve">F9 </w:t></w:r><w:r><w:rPr><w:rFonts w:hint="eastAsia"/></w:rPr><w:t>刷新</w:t></w:r></w:p></w:comment><w:comment w:id="106" w:author="C" w:date="2022-05-17T21:12:00Z" w:initials="C"><w:p w14:paraId="10D63D71" w14:textId="093E8AA1" w:rsidR="00B83D86" w:rsidRDefault="00B83D86"><w:pPr><w:pStyle w:val="a6"/><w:ind w:firstLine="420"/></w:pPr><w:r><w:rPr><w:rStyle w:val="af9"/></w:rPr><w:annotationRef/></w:r><w:r><w:rPr><w:rFonts w:hint="eastAsia"/></w:rPr><w:t>声明没有页码</w:t></w:r></w:p></w:comment><w:comment w:id="107" w:author="C" w:date="2022-05-17T21:12:00Z" w:initials="C"><w:p w14:paraId="3A79860F" w14:textId="4CA5A107" w:rsidR="00B83D86" w:rsidRDefault="00B83D86"><w:pPr><w:pStyle w:val="a6"/><w:ind w:firstLine="420"/></w:pPr><w:r><w:rPr><w:rStyle w:val="af9"/></w:rPr><w:annotationRef/></w:r><w:r><w:rPr><w:rFonts w:hint="eastAsia"/></w:rPr><w:t>英文目录同样可以自动</w:t></w:r><w:r><w:rPr><w:rFonts w:hint="eastAsia"/></w:rPr><w:t>/</w:t></w:r><w:r><w:rPr><w:rFonts w:hint="eastAsia"/></w:rPr><w:t>手动更新，使用方法见「使用说明</w:t></w:r><w:r><w:rPr><w:rFonts w:hint="eastAsia"/></w:rPr><w:t>.</w:t></w:r><w:r><w:t>docx</w:t></w:r><w:r><w:rPr><w:rFonts w:hint="eastAsia"/></w:rPr><w:t>」</w:t></w:r></w:p></w:comment><w:comment w:id="110" w:author="C" w:date="2022-05-17T21:14:00Z" w:initials="C"><w:p w14:paraId="49D348CF" w14:textId="77777777" w:rsidR="00B83D86" w:rsidRDefault="00B83D86" w:rsidP="00426373"><w:pPr><w:ind w:firstLine="420"/><w:rPr><w:color w:val="FF0000"/></w:rPr></w:pPr><w:r><w:rPr><w:rStyle w:val="af9"/></w:rPr><w:annotationRef/></w:r><w:r><w:rPr><w:rFonts w:hint="eastAsia"/><w:color w:val="FF0000"/></w:rPr><w:t>本部分内容非强制性要求，如果论文中所用符号不多，可以省略《主要符号表》。</w:t></w:r></w:p><w:p w14:paraId="42909FDA" w14:textId="77777777" w:rsidR="00B83D86" w:rsidRDefault="00B83D86"><w:pPr><w:pStyle w:val="a6"/><w:ind w:firstLine="480"/></w:pPr></w:p><w:p w14:paraId="338D0449" w14:textId="05139601" w:rsidR="00B83D86" w:rsidRDefault="00B83D86"><w:pPr><w:pStyle w:val="a6"/><w:ind w:firstLine="480"/></w:pPr><w:r><w:rPr><w:rFonts w:hint="eastAsia"/></w:rPr><w:t>如不需要主要符号表，删除此页需保持英文目录与第一节间使用「分节符（奇数页）」分隔，即选中从英文目录后的「分节符（下一页）」到主要符号表后「分节符（奇数页）前」并使用</w:t></w:r><w:r><w:rPr><w:rFonts w:hint="eastAsia"/></w:rPr><w:t xml:space="preserve"> </w:t></w:r><w:r><w:t xml:space="preserve">Delete </w:t></w:r><w:r><w:rPr><w:rFonts w:hint="eastAsia"/></w:rPr><w:t>删除</w:t></w:r></w:p></w:comment><w:comment w:id="121" w:author="C" w:date="2022-05-17T21:23:00Z" w:initials="C"><w:p w14:paraId="459AD798" w14:textId="4E4C8037" w:rsidR="00B83D86" w:rsidRDefault="00B83D86" w:rsidP="006A403A"><w:pPr><w:ind w:firstLine="420"/></w:pPr><w:r><w:rPr><w:rStyle w:val="af9"/></w:rPr><w:annotationRef/></w:r><w:r><w:rPr><w:rFonts w:hint="eastAsia"/></w:rPr><w:t>为了统一格式，模板共有</w:t></w:r><w:r><w:rPr><w:rFonts w:hint="eastAsia"/></w:rPr><w:t>1</w:t></w:r><w:r><w:t>0</w:t></w:r><w:r><w:rPr><w:rFonts w:hint="eastAsia"/></w:rPr><w:t>个和标题相关的样式，分别是“标题</w:t></w:r><w:r><w:rPr><w:rFonts w:hint="eastAsia"/></w:rPr><w:t xml:space="preserve"> </w:t></w:r><w:r><w:t>1</w:t></w:r><w:r><w:rPr><w:rFonts w:hint="eastAsia"/></w:rPr><w:t>-</w:t></w:r><w:r><w:t>7</w:t></w:r><w:r><w:rPr><w:rFonts w:hint="eastAsia"/></w:rPr><w:t>”、“附录标题</w:t></w:r><w:r><w:rPr><w:rFonts w:hint="eastAsia"/></w:rPr><w:t xml:space="preserve"> </w:t></w:r><w:r><w:t>1</w:t></w:r><w:r><w:rPr><w:rFonts w:hint="eastAsia"/></w:rPr><w:t>-</w:t></w:r><w:r><w:t>3</w:t></w:r><w:r><w:rPr><w:rFonts w:hint="eastAsia"/></w:rPr><w:t>”，其中附录标题是基于正文标题创建的，不需要手动修改附录标题样式，只需要修改正文标题样式，附录标题样式可自动更新。</w:t></w:r></w:p></w:comment><w:comment w:id="142" w:author="C" w:date="2022-05-17T21:32:00Z" w:initials="C"><w:p w14:paraId="527F64C7" w14:textId="77777777" w:rsidR="00B83D86" w:rsidRDefault="00B83D86" w:rsidP="00E66EBA"><w:pPr><w:pStyle w:val="a6"/><w:ind w:firstLine="420"/></w:pPr><w:r><w:rPr><w:rStyle w:val="af9"/></w:rPr><w:annotationRef/></w:r><w:r><w:rPr><w:rFonts w:hint="eastAsia"/></w:rPr><w:t>建议插入新的章节的方法：</w:t></w:r></w:p><w:p w14:paraId="7C4A170F" w14:textId="77777777" w:rsidR="00B83D86" w:rsidRDefault="00B83D86" w:rsidP="00E66EBA"><w:pPr><w:pStyle w:val="a6"/><w:ind w:firstLine="480"/></w:pPr></w:p><w:p w14:paraId="5DC7CDED" w14:textId="77777777" w:rsidR="00B83D86" w:rsidRDefault="00B83D86" w:rsidP="00E66EBA"><w:pPr><w:pStyle w:val="a6"/><w:ind w:firstLine="480"/></w:pPr><w:r><w:rPr><w:rFonts w:hint="eastAsia"/></w:rPr><w:t>选中「从上一章结尾的分节符到此一级标题结束」后，复制粘贴</w:t></w:r></w:p><w:p w14:paraId="2A50321F" w14:textId="77777777" w:rsidR="00B83D86" w:rsidRDefault="00B83D86" w:rsidP="00E66EBA"><w:pPr><w:pStyle w:val="a6"/><w:ind w:firstLine="480"/></w:pPr></w:p><w:p w14:paraId="1DC960AB" w14:textId="295BFA69" w:rsidR="00B83D86" w:rsidRDefault="00B83D86" w:rsidP="00E66EBA"><w:pPr><w:pStyle w:val="a6"/><w:ind w:firstLine="480"/></w:pPr><w:r><w:rPr><w:rFonts w:hint="eastAsia"/></w:rPr><w:t>需要注意，为了保证中英目录正常生成，建议始终通过复制原有标题并更改内容的方式，避免手动插入域代码</w:t></w:r></w:p></w:comment><w:comment w:id="161" w:author="C" w:date="2022-05-17T21:39:00Z" w:initials="C"><w:p w14:paraId="7FF8A55D" w14:textId="77777777" w:rsidR="00B83D86" w:rsidRDefault="00B83D86" w:rsidP="00E3097C"><w:pPr><w:pStyle w:val="a6"/><w:ind w:firstLine="420"/></w:pPr><w:r><w:rPr><w:rStyle w:val="af9"/></w:rPr><w:annotationRef/></w:r><w:r><w:rPr><w:rFonts w:hint="eastAsia"/></w:rPr><w:t>参考文献生成建议使用文献管理软件，如</w:t></w:r><w:r><w:rPr><w:rFonts w:hint="eastAsia"/></w:rPr><w:t xml:space="preserve"> </w:t></w:r><w:r><w:t xml:space="preserve">Endnote </w:t></w:r><w:r><w:rPr><w:rFonts w:hint="eastAsia"/></w:rPr><w:t>或</w:t></w:r><w:r><w:rPr><w:rFonts w:hint="eastAsia"/></w:rPr><w:t xml:space="preserve"> </w:t></w:r><w:r><w:t xml:space="preserve">Zotero </w:t></w:r><w:r><w:rPr><w:rFonts w:hint="eastAsia"/></w:rPr><w:t>或</w:t></w:r><w:r><w:rPr><w:rFonts w:hint="eastAsia"/></w:rPr><w:t xml:space="preserve"> </w:t></w:r><w:r><w:t xml:space="preserve">Noteexpress </w:t></w:r><w:r><w:rPr><w:rFonts w:hint="eastAsia"/></w:rPr><w:t>等，具体使用方法可自行在互联网查找</w:t></w:r></w:p><w:p w14:paraId="567C5A15" w14:textId="77777777" w:rsidR="00B83D86" w:rsidRDefault="00B83D86" w:rsidP="00E3097C"><w:pPr><w:pStyle w:val="a6"/><w:ind w:firstLine="480"/></w:pPr></w:p><w:p w14:paraId="66205E49" w14:textId="15683B5F" w:rsidR="00B83D86" w:rsidRDefault="00B83D86" w:rsidP="00E3097C"><w:pPr><w:pStyle w:val="a6"/><w:ind w:firstLine="480"/></w:pPr><w:r><w:rPr><w:rFonts w:hint="eastAsia"/></w:rPr><w:t>注意，使用</w:t></w:r><w:r><w:rPr><w:rFonts w:hint="eastAsia"/></w:rPr><w:t xml:space="preserve"> </w:t></w:r><w:r><w:t xml:space="preserve">GB/T-7714-2015 </w:t></w:r><w:r><w:rPr><w:rFonts w:hint="eastAsia"/></w:rPr><w:t>的相应格式</w:t></w:r></w:p></w:comment><w:comment w:id="168" w:author="C" w:date="2022-05-17T21:40:00Z" w:initials="C"><w:p w14:paraId="22F9EB30" w14:textId="77777777" w:rsidR="00B83D86" w:rsidRDefault="00B83D86"><w:pPr><w:pStyle w:val="a6"/><w:ind w:firstLine="420"/></w:pPr><w:r><w:rPr><w:rStyle w:val="af9"/></w:rPr><w:annotationRef/></w:r><w:r><w:rPr><w:rFonts w:hint="eastAsia"/></w:rPr><w:t>附录标题内容更改的方法见「使用说明</w:t></w:r><w:r><w:t>.docx</w:t></w:r><w:r><w:rPr><w:rFonts w:hint="eastAsia"/></w:rPr><w:t>」</w:t></w:r></w:p><w:p w14:paraId="4CBB09B0" w14:textId="77777777" w:rsidR="00B83D86" w:rsidRDefault="00B83D86"><w:pPr><w:pStyle w:val="a6"/><w:ind w:firstLine="480"/></w:pPr></w:p><w:p w14:paraId="3AE92A56" w14:textId="09CA82A6" w:rsidR="00B83D86" w:rsidRDefault="00B83D86" w:rsidP="00E3097C"><w:pPr><w:ind w:firstLine="480"/></w:pPr><w:r><w:rPr><w:rFonts w:hint="eastAsia"/></w:rPr><w:t>如果不需要附录，删除方法与「主要符号表」的删除方法一致，即保证删除后，前一节与下一节使用「分节符（奇数页）」分搁</w:t></w:r></w:p><w:p w14:paraId="717D80A7" w14:textId="1D738DC4" w:rsidR="00B83D86" w:rsidRDefault="00B83D86"><w:pPr><w:pStyle w:val="a6"/><w:ind w:firstLine="480"/></w:pPr></w:p></w:comment><w:comment w:id="176" w:author="C" w:date="2022-05-17T21:44:00Z" w:initials="C"><w:p w14:paraId="7C2165B2" w14:textId="38B944E0" w:rsidR="00B83D86" w:rsidRDefault="00B83D86" w:rsidP="0076664A"><w:pPr><w:ind w:firstLine="420"/></w:pPr><w:r><w:rPr><w:rStyle w:val="af9"/></w:rPr><w:annotationRef/></w:r><w:r><w:rPr><w:rFonts w:hint="eastAsia"/><w:b/><w:bCs/><w:color w:val="0000FF"/></w:rPr><w:t>用于双盲评审的论文，只列出已发表的学术论文的篇名、发表刊物名称，必须隐去各类论文检索号、期号、卷号、页码；专利号；日期等。</w:t></w:r></w:p></w:comment><w:comment w:id="179" w:author="C" w:date="2022-05-17T21:44:00Z" w:initials="C"><w:p w14:paraId="0DF7B278" w14:textId="77777777" w:rsidR="00B83D86" w:rsidRDefault="00B83D86" w:rsidP="0076664A"><w:pPr><w:ind w:firstLineChars="0" w:firstLine="0"/><w:rPr><w:b/><w:bCs/><w:color w:val="0000FF"/></w:rPr></w:pPr><w:r><w:rPr><w:rStyle w:val="af9"/></w:rPr><w:annotationRef/></w:r><w:r><w:rPr><w:rFonts w:hint="eastAsia"/><w:b/><w:bCs/><w:color w:val="0000FF"/></w:rPr><w:t>1.</w:t></w:r><w:r><w:rPr><w:b/><w:bCs/><w:color w:val="0000FF"/></w:rPr><w:t>填写内容应与</w:t></w:r><w:r><w:rPr><w:b/><w:bCs/><w:color w:val="FF0000"/></w:rPr><w:t>学位（毕业）审批材料</w:t></w:r><w:r><w:rPr><w:b/><w:bCs/><w:color w:val="0000FF"/></w:rPr><w:t>中答辩委员会决议书一致。</w:t></w:r></w:p><w:p w14:paraId="7286649B" w14:textId="77777777" w:rsidR="00B83D86" w:rsidRDefault="00B83D86" w:rsidP="0076664A"><w:pPr><w:ind w:firstLineChars="0" w:firstLine="0"/><w:rPr><w:b/><w:bCs/><w:color w:val="0000FF"/></w:rPr></w:pPr><w:r><w:rPr><w:rFonts w:hint="eastAsia"/><w:b/><w:bCs/><w:color w:val="0000FF"/></w:rPr><w:t>2.</w:t></w:r><w:r><w:rPr><w:rFonts w:hint="eastAsia"/><w:b/><w:bCs/><w:color w:val="0000FF"/></w:rPr><w:t>无需签名。</w:t></w:r></w:p><w:p w14:paraId="3E40AB21" w14:textId="2FBAA680" w:rsidR="00B83D86" w:rsidRDefault="00B83D86" w:rsidP="0076664A"><w:pPr><w:ind w:firstLineChars="0" w:firstLine="0"/></w:pPr><w:r><w:rPr><w:rFonts w:hint="eastAsia"/><w:b/><w:bCs/><w:color w:val="0000FF"/></w:rPr><w:t>3.</w:t></w:r><w:r><w:rPr><w:rFonts w:hint="eastAsia"/><w:b/><w:bCs/><w:color w:val="0000FF"/></w:rPr><w:t>盲审论文仅保留“答辩委员会会议决议”标题</w:t></w:r></w:p></w:comment><w:comment w:id="182" w:author="C" w:date="2022-05-17T21:44:00Z" w:initials="C"><w:p w14:paraId="6ED225BF" w14:textId="641D7326" w:rsidR="00B83D86" w:rsidRDefault="00B83D86" w:rsidP="0076664A"><w:pPr><w:ind w:firstLine="420"/></w:pPr><w:r><w:rPr><w:rStyle w:val="af9"/></w:rPr><w:annotationRef/></w:r><w:r><w:rPr><w:rFonts w:hint="eastAsia"/><w:b/><w:bCs/><w:color w:val="0000FF"/></w:rPr><w:t>盲审论文仅保留“常规评阅人名单”</w:t></w:r><w:r><w:rPr><w:rFonts w:hint="eastAsia"/><w:b/><w:bCs/><w:color w:val="0000FF"/></w:rPr><w:t xml:space="preserve"> </w:t></w:r><w:r><w:rPr><w:rFonts w:hint="eastAsia"/><w:b/><w:bCs/><w:color w:val="0000FF"/></w:rPr><w:t>标题</w:t></w:r></w:p></w:comment><w:comment w:id="184" w:author="C" w:date="2022-05-18T16:29:00Z" w:initials="C"><w:p w14:paraId="0B913A7F" w14:textId="724C3689" w:rsidR="00207A80" w:rsidRPr="00207A80" w:rsidRDefault="00207A80" w:rsidP="00207A80"><w:pPr><w:pStyle w:val="a6"/><w:ind w:firstLine="420"/><w:rPr><w:rFonts w:hint="eastAsia"/><w:b/><w:color w:val="FF0000"/></w:rPr></w:pPr><w:r><w:rPr><w:rStyle w:val="af9"/></w:rPr><w:annotationRef/></w:r><w:r w:rsidRPr="00207A80"><w:rPr><w:rFonts w:hint="eastAsia"/><w:b/><w:color w:val="FF0000"/></w:rPr><w:t>答辩完成后，提交至图书馆版本需要</w:t></w:r><w:r><w:rPr><w:rFonts w:hint="eastAsia"/><w:b/><w:color w:val="FF0000"/></w:rPr><w:t>作者与导师</w:t></w:r><w:r w:rsidRPr="00207A80"><w:rPr><w:rFonts w:hint="eastAsia"/><w:b/><w:color w:val="FF0000"/></w:rPr><w:t>签字</w:t></w:r></w:p><w:p w14:paraId="0D9922D9" w14:textId="46DA886B" w:rsidR="00207A80" w:rsidRDefault="00207A80"><w:pPr><w:pStyle w:val="a6"/><w:ind w:firstLine="480"/></w:pPr></w:p></w:comment></w:comments>